LICENSE
README.md
dash_mdc_neptune/Alert.py
dash_mdc_neptune/Autocomplete.py
dash_mdc_neptune/Box.py
dash_mdc_neptune/Calendar.py
dash_mdc_neptune/Dashboard.py
dash_mdc_neptune/Dropdown.py
dash_mdc_neptune/InputText.py
dash_mdc_neptune/NavBar.py
dash_mdc_neptune/Page.py
dash_mdc_neptune/Section.py
dash_mdc_neptune/SideBar.py
dash_mdc_neptune/Slider.py
dash_mdc_neptune/Tab.py
dash_mdc_neptune/Table.py
dash_mdc_neptune/Toggle.py
dash_mdc_neptune/Typography.py
dash_mdc_neptune/__init__.py
dash_mdc_neptune/_imports_.py
dash_mdc_neptune/dash_mdc_neptune.js
dash_mdc_neptune/dash_mdc_neptune.js.map
dash_mdc_neptune/metadata.json
dash_mdc_neptune/package-info.json
dash_mdc_neptune/themes/__init__.py
dash_mdc_neptune/themes/base.py
dash_mdc_neptune/themes/plotly.py
dash_mdc_neptune/themes/static/logo.png
dash_mdc_neptune/themes/utils.py
package.json
dash_mdc_neptune-0.4.0.dist-info/LICENSE
dash_mdc_neptune-0.4.0.dist-info/METADATA
dash_mdc_neptune-0.4.0.dist-info/WHEEL
dash_mdc_neptune-0.4.0.dist-info/RECORD
