Metadata-Version: 2.1
Name: dash-mdc-neptune
Version: 0.4.0
Summary: Dash Material Design components for the Neptune platform.
Home-page: https://github.com/noosenergy/dash-mdc-neptune
License: MIT
Author: Noos Energy
Author-email: contact@noos.energy
Requires-Python: >=3.11,<4.0
Classifier: Development Status :: 3 - Alpha
Classifier: Intended Audience :: Developers
Classifier: License :: OSI Approved :: MIT License
Classifier: Operating System :: OS Independent
Classifier: Programming Language :: Python :: 3
Classifier: Programming Language :: Python :: 3.11
Classifier: Typing :: Typed
Requires-Dist: dash (>=2.0,<2.10)
